CHANGES.txt
CONTRIBUTORS.txt
LICENSE.txt
README.txt
TODO.txt
bootstrap.py
buildout.cfg
setup.cfg
setup.py
local_tryout/buildout.cfg
src/tha/__init__.py
src/tha.recipe.logcheck.egg-info/PKG-INFO
src/tha.recipe.logcheck.egg-info/SOURCES.txt
src/tha.recipe.logcheck.egg-info/dependency_links.txt
src/tha.recipe.logcheck.egg-info/entry_points.txt
src/tha.recipe.logcheck.egg-info/namespace_packages.txt
src/tha.recipe.logcheck.egg-info/not-zip-safe
src/tha.recipe.logcheck.egg-info/requires.txt
src/tha.recipe.logcheck.egg-info/top_level.txt
src/tha/recipe/__init__.py
src/tha/recipe/logcheck/README.txt
src/tha/recipe/logcheck/__init__.py
src/tha/recipe/logcheck/tests/__init__.py
src/tha/recipe/logcheck/tests/test_docs.py