Metadata-Version: 1.0
Name: tha.recipe.logcheck
Version: 1.1
Summary: Logcheck configuration recipe
Home-page: http://pypi.python.org/pypi/tha.recipe.logcheck
Author: The Health Agency
Author-email: techniek@thehealthagency.com
License: BSD
Platform: UNKNOWN
Classifier: Framework :: Buildout
Classifier: Intended Audience :: Developers
Classifier: Topic :: Software Development :: Build Tools
Classifier: Topic :: Software Development :: Libraries :: Python Modules
Classifier: License :: OSI Approved :: Zope Public License
